LICENSE
README.md
pyproject.toml
setup.cfg
setup.py
kivera/__init__.py
kivera/cloudtenants/__init__.py
kivera/cloudtenants/create.py
kivera/cloudtenants/delete.py
kivera/cloudtenants/get.py
kivera/cloudtenants/list.py
kivera/cloudtenants/update.py
kivera/compliancemappings/__init__.py
kivera/compliancemappings/list.py
kivera/config/__init__.py
kivera/config/get.py
kivera/counters/__init__.py
kivera/counters/get.py
kivera/domainacls/__init__.py
kivera/domainacls/create.py
kivera/domainacls/delete.py
kivera/domainacls/get.py
kivera/domainacls/list.py
kivera/domainacls/update.py
kivera/globalpolicyfunctions/__init__.py
kivera/globalpolicyfunctions/get.py
kivera/globalpolicyfunctions/list.py
kivera/globalservices/__init__.py
kivera/globalservices/list.py
kivera/identities/__init__.py
kivera/identities/create.py
kivera/identities/delete.py
kivera/identities/get.py
kivera/identities/list.py
kivera/identities/update.py
kivera/identityprofiles/__init__.py
kivera/identityprofiles/create.py
kivera/identityprofiles/delete.py
kivera/identityprofiles/get.py
kivera/identityprofiles/list.py
kivera/identityprofiles/update.py
kivera/managedrules/__init__.py
kivera/managedrules/list.py
kivera/memberships/__init__.py
kivera/memberships/create.py
kivera/memberships/delete.py
kivera/memberships/get.py
kivera/memberships/list.py
kivera/memberships/update.py
kivera/metrics/__init__.py
kivera/metrics/getcounterproxymetrics.py
kivera/organizationcredentials/__init__.py
kivera/organizationcredentials/create.py
kivera/organizationcredentials/get.py
kivera/organizationcredentials/update.py
kivera/organizationpolicyfunctions/__init__.py
kivera/organizationpolicyfunctions/create.py
kivera/organizationpolicyfunctions/delete.py
kivera/organizationpolicyfunctions/get.py
kivera/organizationpolicyfunctions/list.py
kivera/organizationpolicyfunctions/update.py
kivera/organizations/__init__.py
kivera/organizations/get.py
kivera/organizations/list.py
kivera/organizations/update.py
kivera_sdk.egg-info/PKG-INFO
kivera_sdk.egg-info/SOURCES.txt
kivera_sdk.egg-info/dependency_links.txt
kivera_sdk.egg-info/requires.txt
kivera_sdk.egg-info/top_level.txt